{
    "addon.mod_url.modulenameplural": "वेबलिंक",
    "core.course": "पाठ्यक्रम",
    "core.courses.availablecourses": "उपलब्ध शिक्षण पाठ्यक्रम",
    "core.courses.categories": "पाठ्यक्रम श्रेणियां",
    "core.courses.courses": "पाठ्यक्रम",
    "core.decsep": ".",
    "core.labelsep": ":",
    "core.listsep": ",",
    "core.mod_url": "वेबलिंक",
    "core.notenrolledprofile": "आप प्रोफ़ाइल नहीं देख सकते क्योंकि यह उपयोगकर्ता इस पाठ्यक्रम में नामांकित नहीं है",
    "core.parentlanguage": "hi",
    "workplace.coursefiles": "पाठ्यक्रम की फ़ाइलें"
}
