{
    "ab": {
        "lang": "ab",
        "md5": "a287b3634bf34065088f66f9618d6ce4",
        "name": "Аԥсуа бызшәа",
        "local": 0,
        "lastupdate": 1735276020,
        "translated": 4
    },
    "af": {
        "lang": "af",
        "md5": "384a133d1f2ac527c1d8ea953e50ee32",
        "name": "Afrikaans",
        "local": 523,
        "lastupdate": 1735276020,
        "translated": 2462
    },
    "sq": {
        "lang": "sq",
        "md5": "0f3bbf7ca8432afddeb32ec5fc15c045",
        "name": "Shqip",
        "local": 233,
        "lastupdate": 1735276020,
        "translated": 467
    },
    "am": {
        "lang": "am",
        "md5": "7490d61b2e554a930c672e182bf925fc",
        "name": " አማርኛ",
        "local": 0,
        "lastupdate": 1735276020,
        "translated": 46
    },
    "ar": {
        "lang": "ar",
        "md5": "04f2cec3601a065c71b32439e7a8e1ff",
        "name": "العربية",
        "local": 770,
        "lastupdate": 1735276020,
        "translated": 2872
    },
    "ar_wp": {
        "lang": "ar_wp",
        "md5": "1244f15a98dd8072a1dcba2bcbd563b5",
        "name": "بالعربي workplace",
        "local": 0,
        "lastupdate": 1735276020,
        "translated": 642
    },
    "an": {
        "lang": "an",
        "md5": "36859e623ca54898657f2f6a0ca1c0b9",
        "name": "Aragonés",
        "local": 0,
        "lastupdate": 1735276020,
        "translated": 1343
    },
    "oc_es": {
        "lang": "oc_es",
        "md5": "6ef6a12a02aae91af537a2ed79663308",
        "name": "Aranés",
        "local": 0,
        "lastupdate": 1735276020,
        "translated": 47
    },
    "hy": {
        "lang": "hy",
        "md5": "09ba68e8e53f63ec51db67788bc83616",
        "name": "Հայերեն",
        "local": 491,
        "lastupdate": 1735276020,
        "translated": 2208
    },
    "ast": {
        "lang": "ast",
        "md5": "185da988258b27830f3fc5e27727a257",
        "name": "Asturianu",
        "local": 0,
        "lastupdate": 1735276021,
        "translated": 861
    },
    "az": {
        "lang": "az",
        "md5": "f709cb157c85b47e80b196860a230110",
        "name": "Azərbaycanca",
        "local": 592,
        "lastupdate": 1735276021,
        "translated": 2383
    },
    "bm": {
        "lang": "bm",
        "md5": "16437bd592f5a04df9dd9107f8e930d6",
        "name": "Bamanankan",
        "local": 0,
        "lastupdate": 1735276021,
        "translated": 3
    },
    "ba": {
        "lang": "ba",
        "md5": "fb3445a378033f92474ace37d6ef97f2",
        "name": "Башҡорт теле",
        "local": 0,
        "lastupdate": 1735276021,
        "translated": 23
    },
    "eu": {
        "lang": "eu",
        "md5": "efda18bdc1b023a0656ae04c16263554",
        "name": "Euskara",
        "local": 770,
        "lastupdate": 1735276021,
        "translated": 2871
    },
    "bar": {
        "lang": "bar",
        "md5": "bafb0e9d4d117f2c0f0e2b31c29af9dc",
        "name": "Bairisch",
        "local": 0,
        "lastupdate": 1735276021,
        "translated": 214
    },
    "be": {
        "lang": "be",
        "md5": "f96604b29e71814cec742303ffe533fc",
        "name": "Беларуская",
        "local": 0,
        "lastupdate": 1735276021,
        "translated": 1622
    },
    "bn": {
        "lang": "bn",
        "md5": "944a0274ae0d10af2dee17d9eb405bb7",
        "name": "বাংলা",
        "local": 1,
        "lastupdate": 1735276021,
        "translated": 1226
    },
    "bi": {
        "lang": "bi",
        "md5": "0acb7e098ae5cbc90e9bac3b63f9b655",
        "name": "Bislama",
        "local": 0,
        "lastupdate": 1735276021,
        "translated": 19
    },
    "bs": {
        "lang": "bs",
        "md5": "212a352354eb7a049b5551ff9f6adbc8",
        "name": "Bosanski",
        "local": 0,
        "lastupdate": 1735276021,
        "translated": 1239
    },
    "br": {
        "lang": "br",
        "md5": "0002b589e7b9e8fc43f544c1d8627d31",
        "name": "Brezhoneg",
        "local": 0,
        "lastupdate": 1735276021,
        "translated": 12
    },
    "bg": {
        "lang": "bg",
        "md5": "61f09ee1890c17fd5a8b0b677f02f410",
        "name": "Български",
        "local": 108,
        "lastupdate": 1735276021,
        "translated": 1699
    },
    "my": {
        "lang": "my",
        "md5": "d2b890ba755119b2ef8ccaf05178728a",
        "name": "ဗမာစာ",
        "local": 0,
        "lastupdate": 1735276021,
        "translated": 1550
    },
    "ca_valencia": {
        "lang": "ca_valencia",
        "md5": "4bb3e37e59c1a50ada2632876b45d048",
        "name": "Català (Valencià)",
        "local": 0,
        "lastupdate": 1735276021,
        "translated": 409
    },
    "ca": {
        "lang": "ca",
        "md5": "08be24eff812cfd2ebac659585d7e663",
        "name": "Català",
        "local": 758,
        "lastupdate": 1735276021,
        "translated": 2858
    },
    "ca_wp": {
        "lang": "ca_wp",
        "md5": "29c618af83267afa6689ee73b1661490",
        "name": "Català",
        "local": 0,
        "lastupdate": 1735276021,
        "translated": 438
    },
    "zh_cn": {
        "lang": "zh_cn",
        "md5": "7f61a38a2b01b2861abbeb7fd91228c6",
        "name": "简体中文",
        "local": 491,
        "lastupdate": 1735276021,
        "translated": 2488
    },
    "zh_cn_wp": {
        "lang": "zh_cn_wp",
        "md5": "8e371c65cd9e54563dec40eb338683df",
        "name": "Workplace 简体中文版",
        "local": 0,
        "lastupdate": 1735276021,
        "translated": 50
    },
    "zh_tw": {
        "lang": "zh_tw",
        "md5": "0830cd60e2abefee6fdf29226de2b9d2",
        "name": "正體中文",
        "local": 466,
        "lastupdate": 1735276021,
        "translated": 2290
    },
    "zh_tw_wp": {
        "lang": "zh_tw_wp",
        "md5": "d84c6483b96ca73f164cd01ce80991df",
        "name": "Workplace 繁體中文版",
        "local": 0,
        "lastupdate": 1735276021,
        "translated": 45
    },
    "hr": {
        "lang": "hr",
        "md5": "4591fd4b4ac60cd334f9ebbbbdf29a16",
        "name": "Hrvatski",
        "local": 161,
        "lastupdate": 1735276021,
        "translated": 2012
    },
    "cs": {
        "lang": "cs",
        "md5": "48f3d8d2ba40abaf888a6c85c0200dcc",
        "name": "Čeština",
        "local": 770,
        "lastupdate": 1735276021,
        "translated": 2771
    },
    "da_kursus": {
        "lang": "da_kursus",
        "md5": "efbff673c78a2ee3d0ad566c886a24b2",
        "name": "Dansk (kursus)",
        "local": 0,
        "lastupdate": 1735276021,
        "translated": 6
    },
    "da": {
        "lang": "da",
        "md5": "893667d88ef4e61b6ebe5824e7c6b3dc",
        "name": "Dansk",
        "local": 750,
        "lastupdate": 1735276021,
        "translated": 2846
    },
    "da_wp": {
        "lang": "da_wp",
        "md5": "bd119b902df01062ba9185a6a6d66782",
        "name": "Dansk",
        "local": 0,
        "lastupdate": 1735276021,
        "translated": 120
    },
    "da_rum": {
        "lang": "da_rum",
        "md5": "e9784f9d86034cdd8cdda4ed08b75487",
        "name": "Dansk Rum",
        "local": 0,
        "lastupdate": 1735276021,
        "translated": 35
    },
    "prs": {
        "lang": "prs",
        "md5": "f4fa86b9e90050a8b961b961ef04ecc8",
        "name": "دری",
        "local": 0,
        "lastupdate": 1735276021,
        "translated": 415
    },
    "dv": {
        "lang": "dv",
        "md5": "b2a4a0960bd0ff58380064d77ae6ebff",
        "name": "ދިވެހި",
        "local": 0,
        "lastupdate": 1735276021,
        "translated": 844
    },
    "nl": {
        "lang": "nl",
        "md5": "6af281bee7c44dce6013ea4b9fffdfd1",
        "name": "Nederlands",
        "local": 770,
        "lastupdate": 1735276021,
        "translated": 2871
    },
    "nl_wp": {
        "lang": "nl_wp",
        "md5": "ab2c88d7d8316b320a65457016ca6a9b",
        "name": "Nederlands",
        "local": 0,
        "lastupdate": 1735276021,
        "translated": 107
    },
    "dz": {
        "lang": "dz",
        "md5": "0d65bd703f8220c230c921b3b8f1acb6",
        "name": "རྫོང་ཁ",
        "local": 0,
        "lastupdate": 1735276021,
        "translated": 1472
    },
    "en": {
        "lang": "en",
        "md5": "b24d854c761f91ae137f67e2f8f69d75",
        "name": "English",
        "local": 770,
        "lastupdate": 1735276021,
        "translated": 2873
    },
    "en_ca": {
        "lang": "en_ca",
        "md5": "a80c9dbbd168773b98e5f3781ffb894a",
        "name": "English (Canada)",
        "local": 0,
        "lastupdate": 1735276021,
        "translated": 6
    },
    "en_kids": {
        "lang": "en_kids",
        "md5": "a95f34efbde6c11009d4a83d08d67657",
        "name": "English",
        "local": 0,
        "lastupdate": 1735276021,
        "translated": 12
    },
    "en_ar": {
        "lang": "en_ar",
        "md5": "aec914c9c8aaff9cd0bc04c8c063a9e5",
        "name": "English (pirate)",
        "local": 0,
        "lastupdate": 1735276021,
        "translated": 92
    },
    "en_us": {
        "lang": "en_us",
        "md5": "efd4f8c6c198d3998870b035f80de02a",
        "name": "English (United States)",
        "local": 1,
        "lastupdate": 1735276021,
        "translated": 32
    },
    "en_us_k12": {
        "lang": "en_us_k12",
        "md5": "235a1a5432eaa30abadaa8748d46463f",
        "name": "English (United States) K12",
        "local": 0,
        "lastupdate": 1735276021,
        "translated": 61
    },
    "en_wp": {
        "lang": "en_wp",
        "md5": "447a7afdee8c6c5a0c31a43a2ef26dd2",
        "name": "English",
        "local": 0,
        "lastupdate": 1735276021,
        "translated": 22
    },
    "en_us_wp": {
        "lang": "en_us_wp",
        "md5": "a78af54c3af1ac32effa5b81408caa3b",
        "name": "English (United States)",
        "local": 0,
        "lastupdate": 1735276021,
        "translated": 5
    },
    "eo": {
        "lang": "eo",
        "md5": "cba6ebe3e5d69b811ddeb80b4a76c97f",
        "name": "Esperanto",
        "local": 0,
        "lastupdate": 1735276021,
        "translated": 582
    },
    "et": {
        "lang": "et",
        "md5": "b28dedda00257b1a1aecc013ace56038",
        "name": "eesti",
        "local": 5,
        "lastupdate": 1735276021,
        "translated": 1934
    },
    "languages": {
        "local": 770,
        "total": 2874
    },
    "ee": {
        "lang": "ee",
        "md5": "52ece1119b2a8b14063f4e272666ec70",
        "name": "Èʋegbe",
        "local": 0,
        "lastupdate": 1735276021,
        "translated": 3
    },
    "fo": {
        "lang": "fo",
        "md5": "f92ee0afaa5e9690c0077e7b3356b5e5",
        "name": "Føroyskt",
        "local": 0,
        "lastupdate": 1735276021,
        "translated": 543
    },
    "fj": {
        "lang": "fj",
        "md5": "9ab2534ec6bdb39bddc6b083dcd47208",
        "name": "VakaViti",
        "local": 0,
        "lastupdate": 1735276021,
        "translated": 220
    },
    "fil": {
        "lang": "fil",
        "md5": "737952e91377658aa22758c5eeaf6adc",
        "name": "Filipino",
        "local": 0,
        "lastupdate": 1735276021,
        "translated": 175
    },
    "fi_co": {
        "lang": "fi_co",
        "md5": "671fc524369d40c3adc7db9f546057c7",
        "name": "Suomi+",
        "local": 0,
        "lastupdate": 1735276021,
        "translated": 38
    },
    "fi": {
        "lang": "fi",
        "md5": "995d16fdc128c0009a1c5533ba99b872",
        "name": "Suomi",
        "local": 293,
        "lastupdate": 1735276021,
        "translated": 2267
    },
    "fr_ca": {
        "lang": "fr_ca",
        "md5": "cede6bdad65aecaa46d3eff98d017bfd",
        "name": "Français (Canada)",
        "local": 0,
        "lastupdate": 1735276021,
        "translated": 165
    },
    "fr": {
        "lang": "fr",
        "md5": "8cdf98d2d896b1ff1f9217092c86323d",
        "name": "Français",
        "local": 770,
        "lastupdate": 1735276021,
        "translated": 2871
    },
    "fr_ca_epi": {
        "lang": "fr_ca_epi",
        "md5": "fb7a919c62c62f340519d2f86a07f2a7",
        "name": "Francais Canada – Épicène",
        "local": 0,
        "lastupdate": 1735276021,
        "translated": 139
    },
    "fr_wp": {
        "lang": "fr_wp",
        "md5": "874219b2373acdbda27f6de02557f212",
        "name": "Français",
        "local": 0,
        "lastupdate": 1735276021,
        "translated": 141
    },
    "fr_incl": {
        "lang": "fr_incl",
        "md5": "35fcbe9bb4d7c68f5671c4e0a4f58248",
        "name": "Français (écriture inclusive)",
        "local": 0,
        "lastupdate": 1735276021,
        "translated": 4
    },
    "gl": {
        "lang": "gl",
        "md5": "be372cf14889467adf94c6cb2e1a7ea3",
        "name": "Galego",
        "local": 749,
        "lastupdate": 1735276021,
        "translated": 2754
    },
    "ka": {
        "lang": "ka",
        "md5": "d4bcd32f0529faa3787ad9625dcb35c0",
        "name": "ქართული",
        "local": 54,
        "lastupdate": 1735276021,
        "translated": 735
    },
    "de_comm": {
        "lang": "de_comm",
        "md5": "2496094445ead09f849139d7880ac2a9",
        "name": "Deutsch (community)",
        "local": 0,
        "lastupdate": 1735276021,
        "translated": 38
    },
    "de_kids": {
        "lang": "de_kids",
        "md5": "7cbf8600904f2179aa9e674afeb1a3e4",
        "name": "Deutsch",
        "local": 0,
        "lastupdate": 1735276021,
        "translated": 74
    },
    "de_du": {
        "lang": "de_du",
        "md5": "bd2b55df60c81bbb06b0dfe900b4bd21",
        "name": "Deutsch (du)",
        "local": 770,
        "lastupdate": 1735276021,
        "translated": 921
    },
    "de": {
        "lang": "de",
        "md5": "a136b2f9683da99ca641f05a96e064ac",
        "name": "Deutsch",
        "local": 770,
        "lastupdate": 1735276021,
        "translated": 2871
    },
    "de_wp": {
        "lang": "de_wp",
        "md5": "af0557ea0d44b6653ad4b8ecc8392905",
        "name": "Deutsch",
        "local": 0,
        "lastupdate": 1735276021,
        "translated": 108
    },
    "de_ch": {
        "lang": "de_ch",
        "md5": "86f7ebae1a12da4fae5cbbec24d94b5d",
        "name": "Deutsch - Schweiz",
        "local": 0,
        "lastupdate": 1735276021,
        "translated": 27
    },
    "el": {
        "lang": "el",
        "md5": "4c9a1a6f3145360a08654469551dc6bb",
        "name": "Ελληνικά",
        "local": 523,
        "lastupdate": 1735276021,
        "translated": 2543
    },
    "el_kids": {
        "lang": "el_kids",
        "md5": "1f8b5340ac8387c481a4fadd0e6b00ae",
        "name": "Ελληνικά",
        "local": 0,
        "lastupdate": 1735276021,
        "translated": 10
    },
    "el_uni": {
        "lang": "el_uni",
        "md5": "9033b658e2352817ffd790d7b6c7800b",
        "name": "Ελληνικά για σχολές",
        "local": 0,
        "lastupdate": 1735276021,
        "translated": 20
    },
    "el_wp": {
        "lang": "el_wp",
        "md5": "4691fe4a51286e7f2e124892cc914aa2",
        "name": "Ελληνικά",
        "local": 326,
        "lastupdate": 1735276021,
        "translated": 2053
    },
    "kl": {
        "lang": "kl",
        "md5": "91e46656ab38045f6426cead5480dae4",
        "name": "Kalaallisut",
        "local": 0,
        "lastupdate": 1735276021,
        "translated": 193
    },
    "gu": {
        "lang": "gu",
        "md5": "ddaccac9369030dcfb7d9abda3d6d04f",
        "name": "ગુજરાતી",
        "local": 0,
        "lastupdate": 1735276021,
        "translated": 717
    },
    "hat": {
        "lang": "hat",
        "md5": "5751937e8aed35accd25d55e490a2949",
        "name": "Kreyòl Ayisyen",
        "local": 0,
        "lastupdate": 1735276021,
        "translated": 25
    },
    "ha": {
        "lang": "ha",
        "md5": "381ec054503bd72e983ba6cb919a89c8",
        "name": "Hausa",
        "local": 0,
        "lastupdate": 1735276021,
        "translated": 3
    },
    "haw": {
        "lang": "haw",
        "md5": "e4bf045b7004a2a6dde5d2f43b5ce283",
        "name": "ʻŌlelo Hawaiʻi",
        "local": 0,
        "lastupdate": 1735276021,
        "translated": 3
    },
    "he_kids": {
        "lang": "he_kids",
        "md5": "6a2b9f3392be09129444790d9da98e3d",
        "name": "עברית בתי־ספר",
        "local": 0,
        "lastupdate": 1735276021,
        "translated": 75
    },
    "he": {
        "lang": "he",
        "md5": "02c0fe11579aeecbbed896d7fd891594",
        "name": "עברית",
        "local": 286,
        "lastupdate": 1735276021,
        "translated": 2081
    },
    "he_wp": {
        "lang": "he_wp",
        "md5": "ba7788bea91368b8167967046dbbc563",
        "name": "עברית עבור Workplace",
        "local": 0,
        "lastupdate": 1735276021,
        "translated": 84
    },
    "hi_kids": {
        "lang": "hi_kids",
        "md5": "c9290199163950d6f8f2532c44ea5090",
        "name": "हिंदी",
        "local": 0,
        "lastupdate": 1735276021,
        "translated": 12
    },
    "hi": {
        "lang": "hi",
        "md5": "ef495b4a005a9c558cabaad6e1da416c",
        "name": "हिंदी",
        "local": 371,
        "lastupdate": 1735276021,
        "translated": 958
    },
    "hi_wp": {
        "lang": "hi_wp",
        "md5": "705edfceb7db090cea9f09e15283c397",
        "name": "वर्कप्लेस  के लिए  हिंदी",
        "local": 0,
        "lastupdate": 1735276021,
        "translated": 3
    },
    "hr_schools": {
        "lang": "hr_schools",
        "md5": "2d4312b3af3089842263add158ef20c8",
        "name": "Hrvatski",
        "local": 0,
        "lastupdate": 1735276021,
        "translated": 4
    },
    "hu": {
        "lang": "hu",
        "md5": "e2f3c5e751d80672d958c359549abf6e",
        "name": "magyar",
        "local": 28,
        "lastupdate": 1735276021,
        "translated": 1938
    },
    "is": {
        "lang": "is",
        "md5": "aeaee371ddf4c9c230ed57f1e87aa3e6",
        "name": "Íslenska",
        "local": 0,
        "lastupdate": 1735276021,
        "translated": 1165
    },
    "ig": {
        "lang": "ig",
        "md5": "8e92049be19cabf1723d725e518f637a",
        "name": "Igbo",
        "local": 0,
        "lastupdate": 1735276021,
        "translated": 6
    },
    "id": {
        "lang": "id",
        "md5": "db3ca72d2a2300900f321947de665fee",
        "name": "Bahasa Indonesia",
        "local": 770,
        "lastupdate": 1735276021,
        "translated": 2852
    },
    "iu": {
        "lang": "iu",
        "md5": "b9e99359c34b0e6c1c853b72088aee7b",
        "name": "ᐃᓄᒃᑎᑐᑦ",
        "local": 0,
        "lastupdate": 1735276022,
        "translated": 3
    },
    "ga": {
        "lang": "ga",
        "md5": "b2379e92773803b0896fcd77ea37e3cd",
        "name": "Gaeilge",
        "local": 0,
        "lastupdate": 1735276022,
        "translated": 666
    },
    "it": {
        "lang": "it",
        "md5": "e28d15b90e89b5a16040a03aa1b0def9",
        "name": "Italiano",
        "local": 367,
        "lastupdate": 1735276022,
        "translated": 2471
    },
    "it_wp": {
        "lang": "it_wp",
        "md5": "fbb0e5e920a6747dc9ed2be84667e0f9",
        "name": "Italiano",
        "local": 0,
        "lastupdate": 1735276022,
        "translated": 18
    },
    "ja_kids": {
        "lang": "ja_kids",
        "md5": "e070b21aa38e952230d172bf6ee228ae",
        "name": "Japanese",
        "local": 0,
        "lastupdate": 1735276022,
        "translated": 34
    },
    "ja": {
        "lang": "ja",
        "md5": "5b6ef857931934f540e62540277af173",
        "name": "日本語",
        "local": 770,
        "lastupdate": 1735276022,
        "translated": 2873
    },
    "ja_wp": {
        "lang": "ja_wp",
        "md5": "787e858719228f57613afe1897d8240d",
        "name": "Workplace準拠の日本語",
        "local": 0,
        "lastupdate": 1735276022,
        "translated": 80
    },
    "kab": {
        "lang": "kab",
        "md5": "2551960bf977026238ec16192609d76e",
        "name": "Taqbaylit",
        "local": 0,
        "lastupdate": 1735276022,
        "translated": 11
    },
    "kn": {
        "lang": "kn",
        "md5": "06841a962f8d668b9b984944ddea482a",
        "name": "ಕನ್ನಡ",
        "local": 302,
        "lastupdate": 1735276022,
        "translated": 499
    },
    "kaa": {
        "lang": "kaa",
        "md5": "6bd3b0fc45565b7806580ce4a03bf29e",
        "name": "Qaraqalpaq tili",
        "local": 0,
        "lastupdate": 1735276022,
        "translated": 3
    },
    "kk": {
        "lang": "kk",
        "md5": "c635f39df0c90f87fc21369e4901ace7",
        "name": "Қазақша",
        "local": 0,
        "lastupdate": 1735276022,
        "translated": 773
    },
    "km": {
        "lang": "km",
        "md5": "b7d60b9c58efa0a675009da87ee00d9e",
        "name": "ខ្មែរ",
        "local": 370,
        "lastupdate": 1735276022,
        "translated": 1923
    },
    "qxr": {
        "lang": "qxr",
        "md5": "fe705facf73477d8cf23f6b4912bad26",
        "name": "Kichwa - Cañar Highland",
        "local": 0,
        "lastupdate": 1735276022,
        "translated": 3
    },
    "rw": {
        "lang": "rw",
        "md5": "ec459b150b6dda7c2269b345f0669bbc",
        "name": "Kinyarwanda",
        "local": 0,
        "lastupdate": 1735276022,
        "translated": 4
    },
    "ko": {
        "lang": "ko",
        "md5": "eb5f02e8740b66213e951b43c3c4400e",
        "name": "한국어",
        "local": 411,
        "lastupdate": 1735276022,
        "translated": 2037
    },
    "ckb": {
        "lang": "ckb",
        "md5": "eab53c8d035951a1db30408257d024cf",
        "name": "سۆرانی",
        "local": 0,
        "lastupdate": 1735276022,
        "translated": 907
    },
    "kmr": {
        "lang": "kmr",
        "md5": "f7e97ffd4ffdd84732250100892d8576",
        "name": "Kurmanji",
        "local": 0,
        "lastupdate": 1735276022,
        "translated": 3
    },
    "fkv": {
        "lang": "fkv",
        "md5": "f134dfcd94e14185376082f852b58ce1",
        "name": "Kvääni",
        "local": 0,
        "lastupdate": 1735276022,
        "translated": 4
    },
    "ky": {
        "lang": "ky",
        "md5": "4c47c2926d515a96341f6235a00c5764",
        "name": "Кыргызча",
        "local": 0,
        "lastupdate": 1735276022,
        "translated": 752
    },
    "lo": {
        "lang": "lo",
        "md5": "5d61370dd7a436eb742b0fc673c796b0",
        "name": "ລາວ",
        "local": 592,
        "lastupdate": 1735276022,
        "translated": 2507
    },
    "la": {
        "lang": "la",
        "md5": "fef134d4e18559c13e99621da7d2ac09",
        "name": "Latin",
        "local": 0,
        "lastupdate": 1735276022,
        "translated": 126
    },
    "lv": {
        "lang": "lv",
        "md5": "5d08bbfd655efa8654c4d92698efacf4",
        "name": "Latviešu",
        "local": 587,
        "lastupdate": 1735276022,
        "translated": 2654
    },
    "lv_wp": {
        "lang": "lv_wp",
        "md5": "a0e80017922078d03618880f074b9337",
        "name": "Latviešu",
        "local": 0,
        "lastupdate": 1735276022,
        "translated": 3
    },
    "lt_uni": {
        "lang": "lt_uni",
        "md5": "c83daad6e3baf2a81dbd50699808817f",
        "name": "Lietuvių (universitetas)",
        "local": 0,
        "lastupdate": 1735276022,
        "translated": 773
    },
    "lt": {
        "lang": "lt",
        "md5": "714db51175ebb3414a17f90513704141",
        "name": "Lietuvių",
        "local": 312,
        "lastupdate": 1735276022,
        "translated": 2316
    },
    "lt_wp": {
        "lang": "lt_wp",
        "md5": "0a17dcb0b80476a0d04b88b861124b41",
        "name": "Lietuvių",
        "local": 0,
        "lastupdate": 1735276022,
        "translated": 46
    },
    "dsb": {
        "lang": "dsb",
        "md5": "554438f956a9cbce59f480b51c2ec267",
        "name": "Dolnoserbski",
        "local": 0,
        "lastupdate": 1735276022,
        "translated": 97
    },
    "lg": {
        "lang": "lg",
        "md5": "b8b4f38c206ca448107e337a18968f5d",
        "name": "Luganda",
        "local": 0,
        "lastupdate": 1735276022,
        "translated": 3
    },
    "smj": {
        "lang": "smj",
        "md5": "6db4e9f169ce1dee838509ac06963026",
        "name": "Lulesamisk",
        "local": 0,
        "lastupdate": 1735276022,
        "translated": 4
    },
    "lb": {
        "lang": "lb",
        "md5": "939f6ce3dde190499ba5a1ac688eb8b6",
        "name": "Lëtzebuergesch",
        "local": 0,
        "lastupdate": 1735276022,
        "translated": 75
    },
    "mk": {
        "lang": "mk",
        "md5": "4c968f2269527f8b36e3eb2975b09e58",
        "name": "Македонски",
        "local": 2,
        "lastupdate": 1735276022,
        "translated": 1310
    },
    "mg": {
        "lang": "mg",
        "md5": "4b847854e7ec946ea50e8e2b7860c4b3",
        "name": "Malagasy",
        "local": 0,
        "lastupdate": 1735276022,
        "translated": 3
    },
    "ml": {
        "lang": "ml",
        "md5": "01a1f712409ed091a6ed7f7753bd6892",
        "name": "മലയാളം",
        "local": 0,
        "lastupdate": 1735276022,
        "translated": 239
    },
    "ms": {
        "lang": "ms",
        "md5": "527d97abf7f205a87cc08d993f3b5ba3",
        "name": "Bahasa Melayu",
        "local": 0,
        "lastupdate": 1735276022,
        "translated": 1507
    },
    "mi_tn": {
        "lang": "mi_tn",
        "md5": "a701a4fc9b47621f2ae6016924b0f228",
        "name": "Māori - Tainui",
        "local": 0,
        "lastupdate": 1735276022,
        "translated": 162
    },
    "mi_wwow": {
        "lang": "mi_wwow",
        "md5": "d08501bd0c0a5367d67c1e2efc958f35",
        "name": "Māori - Waikato",
        "local": 0,
        "lastupdate": 1735276022,
        "translated": 1034
    },
    "mi": {
        "lang": "mi",
        "md5": "b3c21b318c6d229bb77aa8d6930e4ef3",
        "name": "Māori Te Reo",
        "local": 0,
        "lastupdate": 1735276022,
        "translated": 76
    },
    "arn": {
        "lang": "arn",
        "md5": "dffdc373c2ebff69c1cc236661f27229",
        "name": "Mapudungún",
        "local": 0,
        "lastupdate": 1735276022,
        "translated": 11
    },
    "mr": {
        "lang": "mr",
        "md5": "4553524fff5c14bac7446d09e88c1117",
        "name": "मराठी",
        "local": 335,
        "lastupdate": 1735276022,
        "translated": 1077
    },
    "mh": {
        "lang": "mh",
        "md5": "fad391a1e5adf972ac100fd1cf8a69e6",
        "name": "Ebon",
        "local": 0,
        "lastupdate": 1735276022,
        "translated": 18
    },
    "mwl": {
        "lang": "mwl",
        "md5": "7ef95dce0051c8722a57aa71eae5d68c",
        "name": "Mirandés",
        "local": 0,
        "lastupdate": 1735276022,
        "translated": 3
    },
    "mn": {
        "lang": "mn",
        "md5": "82b8bae77cba7d4c0c07a8288737e89a",
        "name": "Монгол",
        "local": 447,
        "lastupdate": 1735276022,
        "translated": 2443
    },
    "mn_mong": {
        "lang": "mn_mong",
        "md5": "7b579919078354ef5fedac3930154c55",
        "name": "Mongolian",
        "local": 0,
        "lastupdate": 1735276022,
        "translated": 9
    },
    "mis": {
        "lang": "mis",
        "md5": "200cdb8e691ac424625247c12cc78003",
        "name": "Crnogorski",
        "local": 0,
        "lastupdate": 1735276022,
        "translated": 3
    },
    "zgh": {
        "lang": "zgh",
        "md5": "23eae57ce8ba7baa5335d9c63e907028",
        "name": "ⵜⴰⵎⴰⵣⵉⵖⵜ",
        "local": 0,
        "lastupdate": 1735276022,
        "translated": 13
    },
    "ne": {
        "lang": "ne",
        "md5": "b0dc7cf08f55e6b1922f0418b247b4b4",
        "name": "नेपाली",
        "local": 0,
        "lastupdate": 1735276022,
        "translated": 234
    },
    "pcm": {
        "lang": "pcm",
        "md5": "11deb718abfb745072b0e3c8097b5c43",
        "name": "Pidgin",
        "local": 0,
        "lastupdate": 1735276022,
        "translated": 11
    },
    "se": {
        "lang": "se",
        "md5": "87f302d4c610793a9d3743d361a492b1",
        "name": "Davvisámegiella",
        "local": 0,
        "lastupdate": 1735276022,
        "translated": 978
    },
    "no_gr": {
        "lang": "no_gr",
        "md5": "bb7a6e91e5f636c97ac42cf15843ba42",
        "name": "Norsk",
        "local": 0,
        "lastupdate": 1735276022,
        "translated": 157
    },
    "no": {
        "lang": "no",
        "md5": "b0596cf7d71d2fd728c3a644f047d866",
        "name": "Norsk",
        "local": 749,
        "lastupdate": 1735276022,
        "translated": 2849
    },
    "nb": {
        "lang": "nb",
        "md5": "1877c8605b5b60bd37dc0ac7b268215f",
        "name": "Norsk - bokmål",
        "local": 0,
        "lastupdate": 1735276022,
        "translated": 9
    },
    "no_wp": {
        "lang": "no_wp",
        "md5": "b3e684fe7482d2af3605abbdcc7de89a",
        "name": "Norsk",
        "local": 0,
        "lastupdate": 1735276022,
        "translated": 108
    },
    "nn": {
        "lang": "nn",
        "md5": "3fe2f258a9d880ca529b5d609f3b6abc",
        "name": "Norsk - nynorsk",
        "local": 0,
        "lastupdate": 1735276022,
        "translated": 378
    },
    "oc_gsc": {
        "lang": "oc_gsc",
        "md5": "897f4e7950fd732885ef53256e0df350",
        "name": "Gascon",
        "local": 0,
        "lastupdate": 1735276022,
        "translated": 1096
    },
    "oc_lnc": {
        "lang": "oc_lnc",
        "md5": "7c31ffff54ddbce3cefd6f1bce70f2bf",
        "name": "Occitan-Lengadocian",
        "local": 0,
        "lastupdate": 1735276022,
        "translated": 1187
    },
    "or": {
        "lang": "or",
        "md5": "5ce9ec0fc52190ca765da96392a7e2c3",
        "name": "ଓଡ଼ିଆ",
        "local": 0,
        "lastupdate": 1735276022,
        "translated": 14
    },
    "om": {
        "lang": "om",
        "md5": "12944a5f6fb1b6ff6fd6057513136b62",
        "name": "Afaan Oromoo",
        "local": 0,
        "lastupdate": 1735276022,
        "translated": 48
    },
    "pap": {
        "lang": "pap",
        "md5": "41997b89e4c019a63f952ffbcb8557cf",
        "name": "Papiamento",
        "local": 0,
        "lastupdate": 1735276022,
        "translated": 50
    },
    "ps": {
        "lang": "ps",
        "md5": "e939653e9db83fd1f116ebcccd1cb260",
        "name": "لیسي",
        "local": 730,
        "lastupdate": 1735276022,
        "translated": 2351
    },
    "fa": {
        "lang": "fa",
        "md5": "63aab24e678a78b2ac443003796f47d4",
        "name": "فارسی",
        "local": 125,
        "lastupdate": 1735276022,
        "translated": 1705
    },
    "pl": {
        "lang": "pl",
        "md5": "032106d5a41300db2fce254874bcca5e",
        "name": "Polski",
        "local": 687,
        "lastupdate": 1735276022,
        "translated": 2683
    },
    "pt_br": {
        "lang": "pt_br",
        "md5": "c546d8f24d96ad09d32ca48ab2d9b160",
        "name": "Português - Brasil",
        "local": 750,
        "lastupdate": 1735276022,
        "translated": 2855
    },
    "pt_br_wp": {
        "lang": "pt_br_wp",
        "md5": "f5dbb5ea43e9317f43d2c239fd4e212c",
        "name": "Português - Brasil",
        "local": 0,
        "lastupdate": 1735276022,
        "translated": 10
    },
    "pt": {
        "lang": "pt",
        "md5": "044b59ccd0ee9b33d241ca454fb95334",
        "name": "Português - Portugal",
        "local": 770,
        "lastupdate": 1735276022,
        "translated": 2871
    },
    "pan": {
        "lang": "pan",
        "md5": "bf8f865fe4629e63a8b846e244f9c826",
        "name": "ਪੰਜਾਬੀ",
        "local": 0,
        "lastupdate": 1735276022,
        "translated": 42
    },
    "qu": {
        "lang": "qu",
        "md5": "42662c09dcd904c4520b439690646817",
        "name": "Quechua",
        "local": 0,
        "lastupdate": 1735276022,
        "translated": 4
    },
    "ro": {
        "lang": "ro",
        "md5": "453dcb929b19607a1d9270aa9a849e8b",
        "name": "Română",
        "local": 770,
        "lastupdate": 1735276022,
        "translated": 2871
    },
    "ro_wp": {
        "lang": "ro_wp",
        "md5": "870317c75108a7289cf0506c76322a8d",
        "name": "Română",
        "local": 0,
        "lastupdate": 1735276022,
        "translated": 1378
    },
    "rm_surs": {
        "lang": "rm_surs",
        "md5": "f8eba36c57dcdfcb044611f9c4bad687",
        "name": "Romansh Sursilvan",
        "local": 0,
        "lastupdate": 1735276022,
        "translated": 541
    },
    "ru": {
        "lang": "ru",
        "md5": "033ce8e14c2e137937ac7e4c26be4275",
        "name": "Русский",
        "local": 355,
        "lastupdate": 1735276022,
        "translated": 2354
    },
    "sm": {
        "lang": "sm",
        "md5": "153cc02649e50fa02aa73f85414c6e28",
        "name": "Samoan",
        "local": 0,
        "lastupdate": 1735276022,
        "translated": 578
    },
    "sa": {
        "lang": "sa",
        "md5": "6470180f6f055aa5e6816482f591e5c7",
        "name": "Sanskrit",
        "local": 0,
        "lastupdate": 1735276022,
        "translated": 23
    },
    "sc": {
        "lang": "sc",
        "md5": "5a6a50309ca204dc94c6d9ac0717a81e",
        "name": "Sard",
        "local": 0,
        "lastupdate": 1735276022,
        "translated": 462
    },
    "gd": {
        "lang": "gd",
        "md5": "b1beee86df042d575eaf14d50a5c10c3",
        "name": "Gàidhlig",
        "local": 0,
        "lastupdate": 1735276022,
        "translated": 221
    },
    "sr_cr": {
        "lang": "sr_cr",
        "md5": "f80239da18d515d32492a2eb870fba3d",
        "name": "Српски",
        "local": 770,
        "lastupdate": 1735276022,
        "translated": 2770
    },
    "sr_lt": {
        "lang": "sr_lt",
        "md5": "9701fb633747f03d527d28c8c8a67203",
        "name": "Srpski",
        "local": 770,
        "lastupdate": 1735276022,
        "translated": 2770
    },
    "tn": {
        "lang": "tn",
        "md5": "e22f49d9583c2d32253cde34d58fe465",
        "name": "Setswana",
        "local": 0,
        "lastupdate": 1735276022,
        "translated": 4
    },
    "scn": {
        "lang": "scn",
        "md5": "828dee9e163b37274e7a55406a4c15ac",
        "name": "Sicilianu",
        "local": 0,
        "lastupdate": 1735276022,
        "translated": 122
    },
    "szl": {
        "lang": "szl",
        "md5": "03010f0bcd4c1048990c94eee332f68a",
        "name": "Ślōnski",
        "local": 466,
        "lastupdate": 1735276022,
        "translated": 2359
    },
    "sd_ap": {
        "lang": "sd_ap",
        "md5": "d8936548945cde8b698557e5cdab8499",
        "name": "سنڌي",
        "local": 0,
        "lastupdate": 1735276022,
        "translated": 4
    },
    "si": {
        "lang": "si",
        "md5": "afd668802b438c7e45feaee8232cdc85",
        "name": "සිංහල",
        "local": 0,
        "lastupdate": 1735276022,
        "translated": 1062
    },
    "sk": {
        "lang": "sk",
        "md5": "b66e9936b6e811df2654ea2fb3424442",
        "name": "Slovenčina",
        "local": 0,
        "lastupdate": 1735276023,
        "translated": 1951
    },
    "sl": {
        "lang": "sl",
        "md5": "40cfe79e132cc200a96182bb394627bf",
        "name": "Slovenščina",
        "local": 491,
        "lastupdate": 1735276023,
        "translated": 2437
    },
    "so": {
        "lang": "so",
        "md5": "977ce31e0435e521d4b135b558be5f12",
        "name": "Soomaali",
        "local": 0,
        "lastupdate": 1735276023,
        "translated": 334
    },
    "sma": {
        "lang": "sma",
        "md5": "c02d328a93fff9f70db2a2f3ead88999",
        "name": "Sørsamisk",
        "local": 0,
        "lastupdate": 1735276023,
        "translated": 4
    },
    "es_ar": {
        "lang": "es_ar",
        "md5": "55f1b367a0def6b38f049195ffde2b77",
        "name": "Español - Argentina",
        "local": 0,
        "lastupdate": 1735276023,
        "translated": 247
    },
    "es_co": {
        "lang": "es_co",
        "md5": "230cf132cf3fe9e2cd7ad702fe9163b0",
        "name": "Español - Colombia",
        "local": 0,
        "lastupdate": 1735276023,
        "translated": 55
    },
    "es_mx": {
        "lang": "es_mx",
        "md5": "881c132ef850d8e90e804daf76dc53b2",
        "name": "Español - México",
        "local": 770,
        "lastupdate": 1735276023,
        "translated": 2872
    },
    "es_mx_kids": {
        "lang": "es_mx_kids",
        "md5": "93086b396eca8c908995e5d868c8fabe",
        "name": "Español - México",
        "local": 0,
        "lastupdate": 1735276023,
        "translated": 18
    },
    "es": {
        "lang": "es",
        "md5": "7bafd40bb107ac8ea2cbe00d689310a6",
        "name": "Español - Internacional",
        "local": 749,
        "lastupdate": 1735276023,
        "translated": 2853
    },
    "es_ve": {
        "lang": "es_ve",
        "md5": "193e85fd86bbfafb93b8057c02beba04",
        "name": "Español - Venezuela",
        "local": 0,
        "lastupdate": 1735276023,
        "translated": 22
    },
    "es_wp": {
        "lang": "es_wp",
        "md5": "54439a0a22c9c4d2be2d631f66464425",
        "name": "Español",
        "local": 0,
        "lastupdate": 1735276023,
        "translated": 90
    },
    "sw": {
        "lang": "sw",
        "md5": "f4a167ff0afaf52fac7d0eb303f38018",
        "name": "Kiswahili",
        "local": 0,
        "lastupdate": 1735276023,
        "translated": 181
    },
    "sv_fi": {
        "lang": "sv_fi",
        "md5": "94060222975981a50d2d66978feea02a",
        "name": "Finlandssvenska",
        "local": 0,
        "lastupdate": 1735276023,
        "translated": 368
    },
    "sv": {
        "lang": "sv",
        "md5": "9e266fe6b60a2167ad4babbf2fdedfd8",
        "name": "Svenska",
        "local": 596,
        "lastupdate": 1735276023,
        "translated": 2563
    },
    "sv_wp": {
        "lang": "sv_wp",
        "md5": "dce4de54a0f78fdeaf0060d3aae31665",
        "name": "Svenska",
        "local": 0,
        "lastupdate": 1735276023,
        "translated": 98
    },
    "tl": {
        "lang": "tl",
        "md5": "5f6abe2d2cb2d0e7129cdd392795e6ff",
        "name": "Tagalog",
        "local": 0,
        "lastupdate": 1735276023,
        "translated": 853
    },
    "tg": {
        "lang": "tg",
        "md5": "fe1920290740c241bf53a8ac477b8cc6",
        "name": "Тоҷикӣ",
        "local": 42,
        "lastupdate": 1735276023,
        "translated": 1292
    },
    "ta_lk": {
        "lang": "ta_lk",
        "md5": "0146456db02c8c17293c55d13c2b6aa8",
        "name": "தமிழ்",
        "local": 0,
        "lastupdate": 1735276023,
        "translated": 971
    },
    "ta": {
        "lang": "ta",
        "md5": "3e1214f974c7309305cf0ed656e8b9c4",
        "name": "Tamil",
        "local": 0,
        "lastupdate": 1735276023,
        "translated": 770
    },
    "tt": {
        "lang": "tt",
        "md5": "f55b59792eb1d98dacd5715d5688d5fa",
        "name": "Татар",
        "local": 0,
        "lastupdate": 1735276023,
        "translated": 18
    },
    "te": {
        "lang": "te",
        "md5": "b5185a36c416bf002f0e998919b11193",
        "name": "తెలుగు ",
        "local": 0,
        "lastupdate": 1735276023,
        "translated": 1166
    },
    "tet": {
        "lang": "tet",
        "md5": "b2f5db695ae101b79f4cbdd7e976d1bd",
        "name": "Tetun Dili",
        "local": 0,
        "lastupdate": 1735276023,
        "translated": 3
    },
    "th": {
        "lang": "th",
        "md5": "1fc27c547d9cd966cbbcf61ef28413b6",
        "name": "Thai",
        "local": 0,
        "lastupdate": 1735276023,
        "translated": 805
    },
    "xct": {
        "lang": "xct",
        "md5": "ffb1724c2bc98799d11545dc9633151f",
        "name": "Tibetan",
        "local": 0,
        "lastupdate": 1735276023,
        "translated": 6
    },
    "ti": {
        "lang": "ti",
        "md5": "d1085b167def6dcaf7697fb3b7fee6d7",
        "name": "ትግርኛ",
        "local": 20,
        "lastupdate": 1735276023,
        "translated": 684
    },
    "tpi": {
        "lang": "tpi",
        "md5": "679320f807d35339676b313031971a95",
        "name": "Tok Pisin",
        "local": 0,
        "lastupdate": 1735276023,
        "translated": 181
    },
    "to": {
        "lang": "to",
        "md5": "73303a127f77104b4686543c143f0d04",
        "name": "Tongan",
        "local": 0,
        "lastupdate": 1735276023,
        "translated": 621
    },
    "tr": {
        "lang": "tr",
        "md5": "eadae3f3386f2a8ba89cdfb0d09bd7af",
        "name": "Türkçe",
        "local": 770,
        "lastupdate": 1735276023,
        "translated": 2871
    },
    "tk": {
        "lang": "tk",
        "md5": "e1a994e268fb5fcb1cdbbc3eb986c011",
        "name": "Turkmen",
        "local": 0,
        "lastupdate": 1735276023,
        "translated": 470
    },
    "uk": {
        "lang": "uk",
        "md5": "a5c4b82fc90e7a16b3c552c786ac5e10",
        "name": "Українська",
        "local": 592,
        "lastupdate": 1735276023,
        "translated": 2597
    },
    "hsb": {
        "lang": "hsb",
        "md5": "85b057ad1a0aff2835eb96ed91326acb",
        "name": "Hornjoserbsce",
        "local": 337,
        "lastupdate": 1735276023,
        "translated": 1663
    },
    "ur": {
        "lang": "ur",
        "md5": "e92e65173a6e3b6ec4cf850f487c559a",
        "name": "اردو",
        "local": 0,
        "lastupdate": 1735276023,
        "translated": 1841
    },
    "ug_lt": {
        "lang": "ug_lt",
        "md5": "5c111506f4d8e21bdf8b847aed055329",
        "name": "Uyghur - latin",
        "local": 0,
        "lastupdate": 1735276023,
        "translated": 3
    },
    "ug_ug": {
        "lang": "ug_ug",
        "md5": "fd56fabd7d3e87c98b33cb8b7c7567e2",
        "name": "ئۇيغۇرچە",
        "local": 0,
        "lastupdate": 1735276023,
        "translated": 223
    },
    "uz": {
        "lang": "uz",
        "md5": "45138782702ba88d3362242b03e4fbdb",
        "name": "O'zbekcha",
        "local": 459,
        "lastupdate": 1735276023,
        "translated": 1712
    },
    "ca_valencia_racv": {
        "lang": "ca_valencia_racv",
        "md5": "d9e8ff89042949c833afdcd912c031c1",
        "name": "Valencià_RACV",
        "local": 0,
        "lastupdate": 1735276023,
        "translated": 4
    },
    "vi": {
        "lang": "vi",
        "md5": "aa8ec5c6b3e7cc54b413980e577a1025",
        "name": "Vietnamese",
        "local": 423,
        "lastupdate": 1735276023,
        "translated": 1908
    },
    "cy": {
        "lang": "cy",
        "md5": "01e1e7fc92fea5c3f575cdf34a5a1e1f",
        "name": "Cymraeg",
        "local": 0,
        "lastupdate": 1735276023,
        "translated": 1146
    },
    "wo": {
        "lang": "wo",
        "md5": "62feeb03c511dbf113c2ca0f86b05bee",
        "name": "Wolof",
        "local": 0,
        "lastupdate": 1735276023,
        "translated": 62
    },
    "xh": {
        "lang": "xh",
        "md5": "54dd27fe06308b0137334d06b54f4ffa",
        "name": "isiXhosa",
        "local": 0,
        "lastupdate": 1735276023,
        "translated": 6
    },
    "yo": {
        "lang": "yo",
        "md5": "ab0d0f117bc05211032967ebfaa19028",
        "name": "Yorùbá",
        "local": 0,
        "lastupdate": 1735276023,
        "translated": 4
    },
    "zu": {
        "lang": "zu",
        "md5": "659c3dcafd020ec42d37ee08da4deff7",
        "name": "isiZulu",
        "local": 0,
        "lastupdate": 1735276023,
        "translated": 520
    },
    "pt_br_kids": {
        "lang": "pt_br_kids",
        "md5": "e86ae308ac0a88c363868cbba68ce034",
        "name": "Português Brasil",
        "local": 0,
        "lastupdate": 1735276022,
        "translated": 73
    },
    "pt_br_uni": {
        "lang": "pt_br_uni",
        "md5": "b473f7069f65b5c95e8864dff29772e7",
        "name": "Português Brasil para Universidades",
        "local": 31,
        "lastupdate": 1735276022,
        "translated": 109
    },
    "ia": {
        "lang": "ia",
        "md5": "60c6c8daed964bad3ad07b9b1fa4e82b",
        "name": "Interlingua",
        "local": 0,
        "lastupdate": 1735276021,
        "translated": 262
    },
    "sgs": {
        "lang": "sgs",
        "md5": "7f4ba783212324bd28791decc8579d3b",
        "name": "Žemaitėškā",
        "local": 0,
        "lastupdate": 1735276022,
        "translated": 3
    },
    "mt": {
        "lang": "mt",
        "md5": "2e38672f94d8f319e121f62b223b6eec",
        "name": "Malti",
        "local": 0,
        "lastupdate": 1735276022,
        "translated": 3
    }
}
