{
    "ab": {
        "lang": "ab",
        "md5": "10b6fad9b90eef665bdc3152836e4cc3",
        "name": "Аԥсуа бызшәа",
        "local": 0,
        "lastupdate": 1707196141,
        "translated": 4
    },
    "af": {
        "lang": "af",
        "md5": "ecf96d1f525540732eef407b55156d08",
        "name": "Afrikaans",
        "local": 533,
        "lastupdate": 1707196141,
        "translated": 2376
    },
    "sq": {
        "lang": "sq",
        "md5": "131e90ad327ecb90b3bb8b3a0de8875a",
        "name": "Shqip",
        "local": 234,
        "lastupdate": 1707196141,
        "translated": 463
    },
    "am": {
        "lang": "am",
        "md5": "6c49f7458a20a6fd6e36fc86970dd2af",
        "name": " አማርኛ",
        "local": 0,
        "lastupdate": 1707196141,
        "translated": 45
    },
    "ar": {
        "lang": "ar",
        "md5": "5215cfe3154218a85506a980de368579",
        "name": "العربية",
        "local": 747,
        "lastupdate": 1707196141,
        "translated": 2650
    },
    "ar_wp": {
        "lang": "ar_wp",
        "md5": "15625311aef3ce78aa589c1e38f131f2",
        "name": "بالعربي workplace",
        "local": 0,
        "lastupdate": 1707196141,
        "translated": 548
    },
    "an": {
        "lang": "an",
        "md5": "555b4bb863efe825306e8a53178d9750",
        "name": "Aragonés",
        "local": 0,
        "lastupdate": 1707196141,
        "translated": 1315
    },
    "oc_es": {
        "lang": "oc_es",
        "md5": "d617693c96783ad0ec27cc5445d9fb26",
        "name": "Aranés",
        "local": 0,
        "lastupdate": 1707196141,
        "translated": 49
    },
    "hy": {
        "lang": "hy",
        "md5": "1da9ae1a3f8afab86857add6f1e11b27",
        "name": "Հայերեն",
        "local": 501,
        "lastupdate": 1707196141,
        "translated": 2196
    },
    "ast": {
        "lang": "ast",
        "md5": "47857c74d989c9a7754ea4b0ba7ca980",
        "name": "Asturianu",
        "local": 0,
        "lastupdate": 1707196141,
        "translated": 848
    },
    "az": {
        "lang": "az",
        "md5": "ab5e626d10727713ce6679b34688781f",
        "name": "Azərbaycanca",
        "local": 603,
        "lastupdate": 1707196141,
        "translated": 2379
    },
    "bm": {
        "lang": "bm",
        "md5": "5df02be0836e49d764976d716868475c",
        "name": "Bamanankan",
        "local": 0,
        "lastupdate": 1707196141,
        "translated": 3
    },
    "ba": {
        "lang": "ba",
        "md5": "a09f2f5a379cde4678de38cc9eb71326",
        "name": "Башҡорт теле",
        "local": 0,
        "lastupdate": 1707196141,
        "translated": 22
    },
    "eu": {
        "lang": "eu",
        "md5": "08aff5bd9bc88922c6187b4b89530698",
        "name": "Euskara",
        "local": 749,
        "lastupdate": 1707196141,
        "translated": 2658
    },
    "bar": {
        "lang": "bar",
        "md5": "e9a5c5e3ad9eea50628e13b2ee4ab01d",
        "name": "Bairisch",
        "local": 0,
        "lastupdate": 1707196141,
        "translated": 212
    },
    "be": {
        "lang": "be",
        "md5": "eaa5e2877b0fa1a343685331708871a8",
        "name": "Беларуская",
        "local": 0,
        "lastupdate": 1707196141,
        "translated": 1116
    },
    "bn": {
        "lang": "bn",
        "md5": "49a4efec7a3c02664973fe74a72b84f9",
        "name": "বাংলা",
        "local": 1,
        "lastupdate": 1707196141,
        "translated": 1201
    },
    "bi": {
        "lang": "bi",
        "md5": "a5e321f74f9e005654c0b78b1b15b417",
        "name": "Bislama",
        "local": 0,
        "lastupdate": 1707196141,
        "translated": 19
    },
    "bs": {
        "lang": "bs",
        "md5": "9dd53267130c70b1975881ba53bacab2",
        "name": "Bosanski",
        "local": 0,
        "lastupdate": 1707196141,
        "translated": 1212
    },
    "br": {
        "lang": "br",
        "md5": "4da088d36a4a197974cc27ec4f1d77fb",
        "name": "Brezhoneg",
        "local": 0,
        "lastupdate": 1707196141,
        "translated": 11
    },
    "bg": {
        "lang": "bg",
        "md5": "37c6c677c57939e25c71d54b8bd62871",
        "name": "Български",
        "local": 110,
        "lastupdate": 1707196141,
        "translated": 1620
    },
    "my": {
        "lang": "my",
        "md5": "43cc2893caecde4fc3ee2fc8c4220470",
        "name": "ဗမာစာ",
        "local": 0,
        "lastupdate": 1707196141,
        "translated": 1461
    },
    "ca_valencia": {
        "lang": "ca_valencia",
        "md5": "8b1ae2b48a1d7b6acc1934b06be3ba92",
        "name": "Català (Valencià)",
        "local": 0,
        "lastupdate": 1707196141,
        "translated": 403
    },
    "ca": {
        "lang": "ca",
        "md5": "ecf506adce40303c57270e566905b596",
        "name": "Català",
        "local": 736,
        "lastupdate": 1707196141,
        "translated": 2625
    },
    "ca_wp": {
        "lang": "ca_wp",
        "md5": "9e6f268ea5f85c2d2ff32c19c5793cda",
        "name": "Català per a Workplace",
        "local": 0,
        "lastupdate": 1707196141,
        "translated": 427
    },
    "zh_cn": {
        "lang": "zh_cn",
        "md5": "0d37264125b8de6b3cf32f0e8d3257d7",
        "name": "简体中文",
        "local": 501,
        "lastupdate": 1707196141,
        "translated": 2369
    },
    "zh_cn_wp": {
        "lang": "zh_cn_wp",
        "md5": "318229b41c4cd84616856718f44a7ddc",
        "name": "Workplace 简体中文版",
        "local": 0,
        "lastupdate": 1707196141,
        "translated": 51
    },
    "zh_tw": {
        "lang": "zh_tw",
        "md5": "ba492910c5a8e6f9faf11c8ec1ca1b17",
        "name": "正體中文",
        "local": 477,
        "lastupdate": 1707196141,
        "translated": 2264
    },
    "zh_tw_wp": {
        "lang": "zh_tw_wp",
        "md5": "d84c6483b96ca73f164cd01ce80991df",
        "name": "Workplace 繁體中文版",
        "local": 0,
        "lastupdate": 1707196141,
        "translated": 46
    },
    "hr": {
        "lang": "hr",
        "md5": "7f9acb19fd1135f100b8b7dd451b4272",
        "name": "Hrvatski",
        "local": 161,
        "lastupdate": 1707196141,
        "translated": 1921
    },
    "cs": {
        "lang": "cs",
        "md5": "a49adfc7a8730250e10af75b65aa8735",
        "name": "Čeština",
        "local": 749,
        "lastupdate": 1707196142,
        "translated": 2644
    },
    "da_kursus": {
        "lang": "da_kursus",
        "md5": "dca0e2c57c804b8c8a646fab08240104",
        "name": "Dansk (kursus)",
        "local": 0,
        "lastupdate": 1707196142,
        "translated": 5
    },
    "da_wp": {
        "lang": "da_wp",
        "md5": "ec4b5bc8892eafcfb33d38235ad0fb28",
        "name": "Dansk til Workplace",
        "local": 0,
        "lastupdate": 1707196142,
        "translated": 113
    },
    "da_rum": {
        "lang": "da_rum",
        "md5": "cbf7d778d55c696cb0b95f4c7766548a",
        "name": "Dansk Rum",
        "local": 0,
        "lastupdate": 1707196142,
        "translated": 35
    },
    "da": {
        "lang": "da",
        "md5": "1d9b5615bf45a1abd079e2ccd8bbb06c",
        "name": "Dansk",
        "local": 749,
        "lastupdate": 1707196142,
        "translated": 2742
    },
    "prs": {
        "lang": "prs",
        "md5": "2c99e4f6fb468b0e5b48f5cb46b35b50",
        "name": "دری",
        "local": 0,
        "lastupdate": 1707196142,
        "translated": 404
    },
    "dv": {
        "lang": "dv",
        "md5": "70a899e5717b7cc32df3ef7754aa3bd9",
        "name": "ދިވެހި",
        "local": 0,
        "lastupdate": 1707196142,
        "translated": 831
    },
    "nl": {
        "lang": "nl",
        "md5": "3696d3b90cdee1bf3a39d6986717fdc6",
        "name": "Nederlands",
        "local": 748,
        "lastupdate": 1707196142,
        "translated": 2741
    },
    "nl_wp": {
        "lang": "nl_wp",
        "md5": "55db852cf936b53592a33697d4518cab",
        "name": "Nederlands Workplace",
        "local": 0,
        "lastupdate": 1707196142,
        "translated": 106
    },
    "dz": {
        "lang": "dz",
        "md5": "541c57d37df64864bf8b3f159f23adf5",
        "name": "རྫོང་ཁ",
        "local": 0,
        "lastupdate": 1707196142,
        "translated": 1443
    },
    "en": {
        "lang": "en",
        "md5": "4572f62e1d490c89f19986ee1da50482",
        "name": "English",
        "local": 749,
        "lastupdate": 1707196142,
        "translated": 2756
    },
    "en_ca": {
        "lang": "en_ca",
        "md5": "a80c9dbbd168773b98e5f3781ffb894a",
        "name": "English (Canada)",
        "local": 0,
        "lastupdate": 1707196142,
        "translated": 6
    },
    "en_kids": {
        "lang": "en_kids",
        "md5": "9b696c76fbf2767cc0cbb46c2c794f4b",
        "name": "English (kids)",
        "local": 0,
        "lastupdate": 1707196142,
        "translated": 12
    },
    "en_ar": {
        "lang": "en_ar",
        "md5": "aec914c9c8aaff9cd0bc04c8c063a9e5",
        "name": "English (pirate)",
        "local": 0,
        "lastupdate": 1707196142,
        "translated": 92
    },
    "en_us": {
        "lang": "en_us",
        "md5": "96137eee48c7652c63395d63705686e8",
        "name": "English (United States)",
        "local": 0,
        "lastupdate": 1707196142,
        "translated": 30
    },
    "en_us_k12": {
        "lang": "en_us_k12",
        "md5": "c8fc948b99b816b2904bfbe51bd339cf",
        "name": "English (United States) K12",
        "local": 0,
        "lastupdate": 1707196142,
        "translated": 60
    },
    "en_wp": {
        "lang": "en_wp",
        "md5": "c1a8e2ab26667aabebe89d5e06d4ab84",
        "name": "English for Workplace",
        "local": 0,
        "lastupdate": 1707196142,
        "translated": 21
    },
    "en_us_wp": {
        "lang": "en_us_wp",
        "md5": "ac624c6218379e215d69fbe66099a2c8",
        "name": "English for Workplace - United States",
        "local": 0,
        "lastupdate": 1707196142,
        "translated": 5
    },
    "eo": {
        "lang": "eo",
        "md5": "abdc988f07245430224c2507f7fe577c",
        "name": "Esperanto",
        "local": 0,
        "lastupdate": 1707196142,
        "translated": 568
    },
    "et": {
        "lang": "et",
        "md5": "741452525d8630c9fffe8c923e9a0c18",
        "name": "eesti",
        "local": 5,
        "lastupdate": 1707196142,
        "translated": 1829
    },
    "languages": {
        "local": 760,
        "total": 2757
    },
    "ee": {
        "lang": "ee",
        "md5": "44c424e624e26b9592b1bf1c50a77229",
        "name": "Èʋegbe",
        "local": 0,
        "lastupdate": 1707196142,
        "translated": 3
    },
    "fo": {
        "lang": "fo",
        "md5": "45e95cd0a7d402929db340e07f0d41fe",
        "name": "Føroyskt",
        "local": 0,
        "lastupdate": 1707196142,
        "translated": 533
    },
    "fj": {
        "lang": "fj",
        "md5": "c3d48ab09a1f866d8f330d5db7edac13",
        "name": "VakaViti",
        "local": 0,
        "lastupdate": 1707196142,
        "translated": 215
    },
    "fil": {
        "lang": "fil",
        "md5": "7eed091a26773abd9872da134c52be3c",
        "name": "Filipino",
        "local": 0,
        "lastupdate": 1707196142,
        "translated": 173
    },
    "fi_co": {
        "lang": "fi_co",
        "md5": "fda701b7dc667a1b379a7cc1aae25e45",
        "name": "Suomi+",
        "local": 0,
        "lastupdate": 1707196142,
        "translated": 34
    },
    "fi": {
        "lang": "fi",
        "md5": "ee5d31791e2d8353d952d8201053fdf5",
        "name": "Suomi",
        "local": 301,
        "lastupdate": 1707196142,
        "translated": 2182
    },
    "fr_ca": {
        "lang": "fr_ca",
        "md5": "3548b33d6ed1b6b4d69e9deecdf3f07a",
        "name": "Français (Canada)",
        "local": 0,
        "lastupdate": 1707196142,
        "translated": 163
    },
    "fr": {
        "lang": "fr",
        "md5": "45af40f72bad03696f5daa9261e55e63",
        "name": "Français",
        "local": 748,
        "lastupdate": 1707196142,
        "translated": 2741
    },
    "fr_ca_epi": {
        "lang": "fr_ca_epi",
        "md5": "f96fa0419e43831429ca700ab57a75ea",
        "name": "Francais Canada – Épicène",
        "local": 0,
        "lastupdate": 1707196142,
        "translated": 137
    },
    "fr_wp": {
        "lang": "fr_wp",
        "md5": "5c6fe383b61ca6e2e96d26ed18409c58",
        "name": "Français pour Workplace",
        "local": 0,
        "lastupdate": 1707196142,
        "translated": 140
    },
    "fr_incl": {
        "lang": "fr_incl",
        "md5": "35fcbe9bb4d7c68f5671c4e0a4f58248",
        "name": "Français (écriture inclusive)",
        "local": 0,
        "lastupdate": 1707196142,
        "translated": 4
    },
    "gl": {
        "lang": "gl",
        "md5": "d471fae7032ace8122f09b72ff3559c1",
        "name": "Galego",
        "local": 747,
        "lastupdate": 1707196142,
        "translated": 2645
    },
    "ka": {
        "lang": "ka",
        "md5": "f8f35a975f88a0b2df6c82b12bcaf8ff",
        "name": "ქართული",
        "local": 53,
        "lastupdate": 1707196142,
        "translated": 667
    },
    "de_comm": {
        "lang": "de_comm",
        "md5": "2496094445ead09f849139d7880ac2a9",
        "name": "Deutsch (community)",
        "local": 0,
        "lastupdate": 1707196142,
        "translated": 37
    },
    "de_kids": {
        "lang": "de_kids",
        "md5": "fd4446d41d1265f46ef1a647824daccc",
        "name": "Deutsch (kids)",
        "local": 0,
        "lastupdate": 1707196142,
        "translated": 66
    },
    "de_du": {
        "lang": "de_du",
        "md5": "2197239300bba7dd149aa36cd88ee34d",
        "name": "Deutsch (du)",
        "local": 748,
        "lastupdate": 1707196142,
        "translated": 892
    },
    "de": {
        "lang": "de",
        "md5": "6fc648f3581fc2771c07652be863072b",
        "name": "Deutsch",
        "local": 749,
        "lastupdate": 1707196142,
        "translated": 2742
    },
    "de_wp": {
        "lang": "de_wp",
        "md5": "45a739c20b10fb734fdad9fc6bb3f9cf",
        "name": "Deutsch",
        "local": 0,
        "lastupdate": 1707196142,
        "translated": 107
    },
    "de_ch": {
        "lang": "de_ch",
        "md5": "6ac3cb87106c4156e6dde09bf0fd8014",
        "name": "Deutsch - Schweiz",
        "local": 0,
        "lastupdate": 1707196142,
        "translated": 25
    },
    "el": {
        "lang": "el",
        "md5": "20e590c566ef1b563a516ad70af7fc27",
        "name": "Ελληνικά",
        "local": 533,
        "lastupdate": 1707196142,
        "translated": 2365
    },
    "el_kids": {
        "lang": "el_kids",
        "md5": "bb8891f5749822263370fff98181f440",
        "name": "Ελληνικά για παιδιά",
        "local": 0,
        "lastupdate": 1707196142,
        "translated": 10
    },
    "el_uni": {
        "lang": "el_uni",
        "md5": "9033b658e2352817ffd790d7b6c7800b",
        "name": "Ελληνικά για σχολές",
        "local": 0,
        "lastupdate": 1707196142,
        "translated": 20
    },
    "el_wp": {
        "lang": "el_wp",
        "md5": "f634e81438afd6ab06fe3c76858c7fae",
        "name": "Ελληνικά για χώρους εργασίας",
        "local": 334,
        "lastupdate": 1707196142,
        "translated": 1965
    },
    "kl": {
        "lang": "kl",
        "md5": "52444e4040a4ed862c7c6aeed8f34426",
        "name": "Kalaallisut",
        "local": 0,
        "lastupdate": 1707196142,
        "translated": 192
    },
    "gu": {
        "lang": "gu",
        "md5": "454fec113f31da0da9789c24d93acac7",
        "name": "ગુજરાતી",
        "local": 0,
        "lastupdate": 1707196142,
        "translated": 705
    },
    "hat": {
        "lang": "hat",
        "md5": "7ac6ca1e386459b6d1d73bdfc93ee9f0",
        "name": "Kreyòl Ayisyen",
        "local": 0,
        "lastupdate": 1707196142,
        "translated": 25
    },
    "ha": {
        "lang": "ha",
        "md5": "65d8610a2c7b73d477b441228c6638cb",
        "name": "Hausa",
        "local": 0,
        "lastupdate": 1707196142,
        "translated": 3
    },
    "haw": {
        "lang": "haw",
        "md5": "1e6a84c13d5f1e6b39799031277ea8e2",
        "name": "ʻŌlelo Hawaiʻi",
        "local": 0,
        "lastupdate": 1707196142,
        "translated": 3
    },
    "he_kids": {
        "lang": "he_kids",
        "md5": "b625e3d95db969f2e4368756df3b0877",
        "name": "עברית בתי־ספר",
        "local": 0,
        "lastupdate": 1707196142,
        "translated": 72
    },
    "he": {
        "lang": "he",
        "md5": "aa740528ed69a6aad26fb4f343114423",
        "name": "עברית",
        "local": 258,
        "lastupdate": 1707196142,
        "translated": 1966
    },
    "he_wp": {
        "lang": "he_wp",
        "md5": "5e75a8399d524beda1cadbe1318a7dc4",
        "name": "עברית עבור Workplace",
        "local": 0,
        "lastupdate": 1707196142,
        "translated": 86
    },
    "hi_kids": {
        "lang": "hi_kids",
        "md5": "c9290199163950d6f8f2532c44ea5090",
        "name": "हिंदी",
        "local": 0,
        "lastupdate": 1707196142,
        "translated": 12
    },
    "hi": {
        "lang": "hi",
        "md5": "6e274c3cb2b69c1c5ea3dec8e8fbc68c",
        "name": "हिंदी",
        "local": 379,
        "lastupdate": 1707196142,
        "translated": 957
    },
    "hi_wp": {
        "lang": "hi_wp",
        "md5": "705edfceb7db090cea9f09e15283c397",
        "name": "वर्कप्लेस  के लिए  हिंदी",
        "local": 0,
        "lastupdate": 1707196142,
        "translated": 3
    },
    "hr_schools": {
        "lang": "hr_schools",
        "md5": "2d4312b3af3089842263add158ef20c8",
        "name": "Hrvatski",
        "local": 0,
        "lastupdate": 1707196142,
        "translated": 4
    },
    "hu": {
        "lang": "hu",
        "md5": "471f085e4fd0d70ebc2ef2bd1e7e09e8",
        "name": "magyar",
        "local": 29,
        "lastupdate": 1707196142,
        "translated": 1838
    },
    "is": {
        "lang": "is",
        "md5": "ea71e7887908b3dc1f167140842d7826",
        "name": "Íslenska",
        "local": 0,
        "lastupdate": 1707196142,
        "translated": 1139
    },
    "ig": {
        "lang": "ig",
        "md5": "be9b883c7d622525b7ca981886c67700",
        "name": "Igbo",
        "local": 0,
        "lastupdate": 1707196142,
        "translated": 6
    },
    "id": {
        "lang": "id",
        "md5": "0b34d9aeb461144eaa69c367dbda190b",
        "name": "Bahasa Indonesia",
        "local": 564,
        "lastupdate": 1707196142,
        "translated": 2457
    },
    "iu": {
        "lang": "iu",
        "md5": "8548e0621898552b847561fb2a5eb49a",
        "name": "ᐃᓄᒃᑎᑐᑦ",
        "local": 0,
        "lastupdate": 1707196142,
        "translated": 3
    },
    "ga": {
        "lang": "ga",
        "md5": "42c33be9695ce98f173fd58adf3a860c",
        "name": "Gaeilge",
        "local": 0,
        "lastupdate": 1707196142,
        "translated": 650
    },
    "it": {
        "lang": "it",
        "md5": "c20b6b8cce222a7f7054fb5e33bb78e6",
        "name": "Italiano",
        "local": 375,
        "lastupdate": 1707196142,
        "translated": 2359
    },
    "it_wp": {
        "lang": "it_wp",
        "md5": "fbb0e5e920a6747dc9ed2be84667e0f9",
        "name": "Italiano",
        "local": 0,
        "lastupdate": 1707196142,
        "translated": 18
    },
    "ja_kids": {
        "lang": "ja_kids",
        "md5": "d08fb08e8fc04a9633f0ebcf4b7cb865",
        "name": "Japanese (kids)",
        "local": 0,
        "lastupdate": 1707196142,
        "translated": 33
    },
    "ja": {
        "lang": "ja",
        "md5": "6617e84ffc032edcb640afe87cf0c5bc",
        "name": "日本語",
        "local": 748,
        "lastupdate": 1707196142,
        "translated": 2741
    },
    "ja_wp": {
        "lang": "ja_wp",
        "md5": "19845a7ee2ceb4cdcf578aa4dc177890",
        "name": "Workplace準拠の日本語",
        "local": 0,
        "lastupdate": 1707196142,
        "translated": 79
    },
    "kab": {
        "lang": "kab",
        "md5": "ba15027b87d3145e632fb13a5b6e13c3",
        "name": "Taqbaylit",
        "local": 0,
        "lastupdate": 1707196142,
        "translated": 11
    },
    "kn": {
        "lang": "kn",
        "md5": "24d7c296dc1fffa0024390a6b1b12970",
        "name": "ಕನ್ನಡ",
        "local": 309,
        "lastupdate": 1707196142,
        "translated": 493
    },
    "kaa": {
        "lang": "kaa",
        "md5": "64f6353621e1b61fcb000000b117fd76",
        "name": "Qaraqalpaq tili",
        "local": 0,
        "lastupdate": 1707196142,
        "translated": 3
    },
    "kk": {
        "lang": "kk",
        "md5": "d81b95218cb3fe22cae9ddebaea8e06e",
        "name": "Қазақша",
        "local": 0,
        "lastupdate": 1707196142,
        "translated": 755
    },
    "km": {
        "lang": "km",
        "md5": "0f3d1c71b935f14ceaa842a00b3eebd4",
        "name": "ខ្មែរ",
        "local": 378,
        "lastupdate": 1707196142,
        "translated": 1909
    },
    "qxr": {
        "lang": "qxr",
        "md5": "92401c45aea520061765350bad137919",
        "name": "Kichwa - Cañar Highland",
        "local": 0,
        "lastupdate": 1707196142,
        "translated": 3
    },
    "rw": {
        "lang": "rw",
        "md5": "757e4d1622e4bd8a0132825fce523591",
        "name": "Kinyarwanda",
        "local": 0,
        "lastupdate": 1707196142,
        "translated": 4
    },
    "ko": {
        "lang": "ko",
        "md5": "7104dc9a67c0447c9831e6509e8ee62a",
        "name": "한국어",
        "local": 421,
        "lastupdate": 1707196142,
        "translated": 2022
    },
    "ckb": {
        "lang": "ckb",
        "md5": "f8d3714c4cc9a9003e9a621ca471fd93",
        "name": "سۆرانی",
        "local": 0,
        "lastupdate": 1707196142,
        "translated": 888
    },
    "kmr": {
        "lang": "kmr",
        "md5": "73b5edcf64bd201da9b19ce0bb4e6c47",
        "name": "Kurmanji",
        "local": 0,
        "lastupdate": 1707196142,
        "translated": 3
    },
    "fkv": {
        "lang": "fkv",
        "md5": "8b2b7a29ee9539fb01a34f48258e9e85",
        "name": "Kvääni",
        "local": 0,
        "lastupdate": 1707196142,
        "translated": 4
    },
    "ky": {
        "lang": "ky",
        "md5": "a7f9ef6e9e2e8da9217e8665c57c7a35",
        "name": "Кыргызча",
        "local": 0,
        "lastupdate": 1707196142,
        "translated": 744
    },
    "lo": {
        "lang": "lo",
        "md5": "72bf576bb652bf681fb7c0e33c7f3cc9",
        "name": "ລາວ",
        "local": 603,
        "lastupdate": 1707196142,
        "translated": 2418
    },
    "la": {
        "lang": "la",
        "md5": "f1a63ff39aea9d1108ddb9ec4906c94a",
        "name": "Latin",
        "local": 0,
        "lastupdate": 1707196142,
        "translated": 127
    },
    "lv": {
        "lang": "lv",
        "md5": "71a4c877b851865cdd6743e2f92b7bbf",
        "name": "Latviešu",
        "local": 598,
        "lastupdate": 1707196142,
        "translated": 2565
    },
    "lv_wp": {
        "lang": "lv_wp",
        "md5": "a7ff50ab54d1c57f8c0bcc031739b6f3",
        "name": "Latviešu (Workplace)",
        "local": 0,
        "lastupdate": 1707196142,
        "translated": 3
    },
    "lt_uni": {
        "lang": "lt_uni",
        "md5": "44c54cbc821840d90ce60eb01608f539",
        "name": "Lietuvių (universitetas)",
        "local": 0,
        "lastupdate": 1707196142,
        "translated": 751
    },
    "lt": {
        "lang": "lt",
        "md5": "e14dd53c8c6e51e9f9d680be38f0f463",
        "name": "Lietuvių",
        "local": 318,
        "lastupdate": 1707196143,
        "translated": 2215
    },
    "lt_wp": {
        "lang": "lt_wp",
        "md5": "cf3f823498f3150124ec1dc91d208b86",
        "name": "Lietuvių (Workplace)",
        "local": 0,
        "lastupdate": 1707196143,
        "translated": 44
    },
    "dsb": {
        "lang": "dsb",
        "md5": "02b31aa4e7cd1efa2d2b193efcf5fcda",
        "name": "Dolnoserbski",
        "local": 0,
        "lastupdate": 1707196143,
        "translated": 95
    },
    "lg": {
        "lang": "lg",
        "md5": "277efdcf340d9894c827eae17b89f8fe",
        "name": "Luganda",
        "local": 0,
        "lastupdate": 1707196143,
        "translated": 3
    },
    "smj": {
        "lang": "smj",
        "md5": "a4b843760b8449d75b0528879baf217c",
        "name": "Lulesamisk",
        "local": 0,
        "lastupdate": 1707196143,
        "translated": 4
    },
    "lb": {
        "lang": "lb",
        "md5": "3dc1cc5f7cc62ac6c5b2e3e5ae38520d",
        "name": "Lëtzebuergesch",
        "local": 0,
        "lastupdate": 1707196143,
        "translated": 74
    },
    "mk": {
        "lang": "mk",
        "md5": "94a6fbf42e7f141b551ff45418ae6c1c",
        "name": "Македонски",
        "local": 2,
        "lastupdate": 1707196143,
        "translated": 1246
    },
    "mg": {
        "lang": "mg",
        "md5": "f569b914a5bb9e033b1b5064bb9b6086",
        "name": "Malagasy",
        "local": 0,
        "lastupdate": 1707196143,
        "translated": 3
    },
    "ml": {
        "lang": "ml",
        "md5": "55081e3fadca6778b77529e0eccc8d83",
        "name": "മലയാളം",
        "local": 0,
        "lastupdate": 1707196143,
        "translated": 232
    },
    "ms": {
        "lang": "ms",
        "md5": "6b16d14c1bf1726e9ac5f523377ba613",
        "name": "Bahasa Melayu",
        "local": 0,
        "lastupdate": 1707196143,
        "translated": 617
    },
    "mi_tn": {
        "lang": "mi_tn",
        "md5": "15f1bdab96745bf5312eb96f7957209c",
        "name": "Māori - Tainui",
        "local": 0,
        "lastupdate": 1707196143,
        "translated": 159
    },
    "mi_wwow": {
        "lang": "mi_wwow",
        "md5": "978e1d6d9158601400771750a42e012c",
        "name": "Māori - Waikato",
        "local": 0,
        "lastupdate": 1707196143,
        "translated": 1015
    },
    "mi": {
        "lang": "mi",
        "md5": "05c4cae899fb6c900762dce56f851a24",
        "name": "Māori Te Reo",
        "local": 0,
        "lastupdate": 1707196143,
        "translated": 70
    },
    "arn": {
        "lang": "arn",
        "md5": "5fbeb551776569886a4c2384e214edd3",
        "name": "Mapudungún",
        "local": 0,
        "lastupdate": 1707196143,
        "translated": 10
    },
    "mr": {
        "lang": "mr",
        "md5": "a6411b893c76378ccf3c42c25b3a976c",
        "name": "मराठी",
        "local": 343,
        "lastupdate": 1707196143,
        "translated": 1074
    },
    "mh": {
        "lang": "mh",
        "md5": "c8d2860a4ff6011cd653e11fa096960c",
        "name": "Ebon",
        "local": 0,
        "lastupdate": 1707196143,
        "translated": 17
    },
    "mwl": {
        "lang": "mwl",
        "md5": "abb7b03769b748009f7997a191037a86",
        "name": "Mirandés",
        "local": 0,
        "lastupdate": 1707196143,
        "translated": 3
    },
    "mn": {
        "lang": "mn",
        "md5": "5b086d7adf7afa8cab08580cacbcd51f",
        "name": "Монгол",
        "local": 457,
        "lastupdate": 1707196143,
        "translated": 2351
    },
    "mn_mong": {
        "lang": "mn_mong",
        "md5": "7b579919078354ef5fedac3930154c55",
        "name": "Mongolian",
        "local": 0,
        "lastupdate": 1707196143,
        "translated": 8
    },
    "mis": {
        "lang": "mis",
        "md5": "872c95adb78b2a33a4f07b3c812d430b",
        "name": "Crnogorski",
        "local": 0,
        "lastupdate": 1707196143,
        "translated": 3
    },
    "zgh": {
        "lang": "zgh",
        "md5": "58d50297ebce79980b4bcbd3d3a0036d",
        "name": "ⵜⴰⵎⴰⵣⵉⵖⵜ",
        "local": 0,
        "lastupdate": 1707196143,
        "translated": 11
    },
    "ne": {
        "lang": "ne",
        "md5": "57b9cfaebe09afa863288017da93edf2",
        "name": "नेपाली",
        "local": 0,
        "lastupdate": 1707196143,
        "translated": 224
    },
    "pcm": {
        "lang": "pcm",
        "md5": "ae17f166da481d7d1508c18604ae52bf",
        "name": "Pidgin",
        "local": 0,
        "lastupdate": 1707196143,
        "translated": 9
    },
    "se": {
        "lang": "se",
        "md5": "0fb59d81465a21c959d4ecd08fe6ade9",
        "name": "Davvisámegiella",
        "local": 0,
        "lastupdate": 1707196143,
        "translated": 952
    },
    "no_gr": {
        "lang": "no_gr",
        "md5": "b1bf39ef6ae94e4934d502712b137343",
        "name": "Norsk",
        "local": 0,
        "lastupdate": 1707196143,
        "translated": 155
    },
    "no": {
        "lang": "no",
        "md5": "cdd6679ac51dcdd0b9babc4c6798cd9f",
        "name": "Norsk",
        "local": 748,
        "lastupdate": 1707196143,
        "translated": 2741
    },
    "nb": {
        "lang": "nb",
        "md5": "0231f14724f96257588a76e1daee0594",
        "name": "Norsk - bokmål",
        "local": 0,
        "lastupdate": 1707196143,
        "translated": 4
    },
    "no_wp": {
        "lang": "no_wp",
        "md5": "6bc0176d5e88b2196c73161379063ab4",
        "name": "Norsk Workplace",
        "local": 0,
        "lastupdate": 1707196143,
        "translated": 107
    },
    "nn": {
        "lang": "nn",
        "md5": "3069a6dfa96a0bdb772941491e69a730",
        "name": "Norsk - nynorsk",
        "local": 0,
        "lastupdate": 1707196143,
        "translated": 370
    },
    "oc_gsc": {
        "lang": "oc_gsc",
        "md5": "4dc3f4f78831c65e85fddc9486d1d5ee",
        "name": "Gascon",
        "local": 0,
        "lastupdate": 1707196143,
        "translated": 1082
    },
    "oc_lnc": {
        "lang": "oc_lnc",
        "md5": "f38301bfa7b7b77f47a0c5fb71ab01e0",
        "name": "Occitan-Lengadocian",
        "local": 0,
        "lastupdate": 1707196143,
        "translated": 1165
    },
    "or": {
        "lang": "or",
        "md5": "86c050ad14196411a5dd777a68259348",
        "name": "ଓଡ଼ିଆ",
        "local": 0,
        "lastupdate": 1707196143,
        "translated": 13
    },
    "om": {
        "lang": "om",
        "md5": "c6e0a0d63953efd7a9574015699ea602",
        "name": "Afaan Oromoo",
        "local": 0,
        "lastupdate": 1707196143,
        "translated": 47
    },
    "pap": {
        "lang": "pap",
        "md5": "1b0168f9500876dbb731dad5e7c93e71",
        "name": "Papiamento",
        "local": 0,
        "lastupdate": 1707196143,
        "translated": 52
    },
    "ps": {
        "lang": "ps",
        "md5": "80a7ac633f3d72cc3cf0d1791efb941d",
        "name": "لیسي",
        "local": 747,
        "lastupdate": 1707196143,
        "translated": 2291
    },
    "fa": {
        "lang": "fa",
        "md5": "463c72804b05f8bb0da2c5539c0b0245",
        "name": "فارسی",
        "local": 127,
        "lastupdate": 1707196143,
        "translated": 1666
    },
    "pl": {
        "lang": "pl",
        "md5": "109995ddee3fd3005a3b11e7f0a6c524",
        "name": "Polski",
        "local": 704,
        "lastupdate": 1707196143,
        "translated": 2594
    },
    "pt_br": {
        "lang": "pt_br",
        "md5": "a1b78c7dd5f44db9d49d5b5d244d4be1",
        "name": "Português - Brasil",
        "local": 747,
        "lastupdate": 1707196143,
        "translated": 2711
    },
    "pt_br_wp": {
        "lang": "pt_br_wp",
        "md5": "24ff52bbf567c50ae4c836d4acff7a9e",
        "name": "Português para Workplace",
        "local": 0,
        "lastupdate": 1707196143,
        "translated": 10
    },
    "pt": {
        "lang": "pt",
        "md5": "ba011cca2c7e6f5f972cd245755bf9e3",
        "name": "Português - Portugal",
        "local": 749,
        "lastupdate": 1707196143,
        "translated": 2742
    },
    "pan": {
        "lang": "pan",
        "md5": "ced9742ee0b88035f28b5dba52876161",
        "name": "ਪੰਜਾਬੀ",
        "local": 0,
        "lastupdate": 1707196143,
        "translated": 44
    },
    "qu": {
        "lang": "qu",
        "md5": "988eed460e17d3e098a0ecd0415ff5be",
        "name": "Quechua",
        "local": 0,
        "lastupdate": 1707196143,
        "translated": 4
    },
    "ro": {
        "lang": "ro",
        "md5": "c94e7c152325aa53e5270289c89041d7",
        "name": "Română",
        "local": 749,
        "lastupdate": 1707196143,
        "translated": 2744
    },
    "ro_wp": {
        "lang": "ro_wp",
        "md5": "087e36c54cd0299dd61b7fa8074237be",
        "name": "Română Workplace",
        "local": 0,
        "lastupdate": 1707196143,
        "translated": 1357
    },
    "rm_surs": {
        "lang": "rm_surs",
        "md5": "438d7c0ccf4dadd4d448875d3ee6c503",
        "name": "Romansh Sursilvan",
        "local": 0,
        "lastupdate": 1707196143,
        "translated": 536
    },
    "ru": {
        "lang": "ru",
        "md5": "a9ed3fe35d635e5d886fe9bd31d3cac2",
        "name": "Русский",
        "local": 363,
        "lastupdate": 1707196143,
        "translated": 2254
    },
    "sm": {
        "lang": "sm",
        "md5": "77a284cf72d48fd2a29b08a73155ce18",
        "name": "Samoan",
        "local": 0,
        "lastupdate": 1707196143,
        "translated": 577
    },
    "sa": {
        "lang": "sa",
        "md5": "84bf2260549e383f8b723e4344a58b31",
        "name": "Sanskrit",
        "local": 0,
        "lastupdate": 1707196143,
        "translated": 22
    },
    "sc": {
        "lang": "sc",
        "md5": "93c2c66da233bd3701d6dc6327638f53",
        "name": "Sard",
        "local": 0,
        "lastupdate": 1707196143,
        "translated": 450
    },
    "gd": {
        "lang": "gd",
        "md5": "2227b1a8dca9e5eb08ebcde3bdc5238c",
        "name": "Gàidhlig",
        "local": 0,
        "lastupdate": 1707196143,
        "translated": 217
    },
    "sr_cr": {
        "lang": "sr_cr",
        "md5": "aec76d798916d004923d3a4b87f93df1",
        "name": "Српски",
        "local": 391,
        "lastupdate": 1707196143,
        "translated": 2285
    },
    "sr_lt": {
        "lang": "sr_lt",
        "md5": "e5b893a5fdd33a70bdc92481144bdb2e",
        "name": "Srpski",
        "local": 391,
        "lastupdate": 1707196143,
        "translated": 2285
    },
    "tn": {
        "lang": "tn",
        "md5": "81a54be8d781f14134831a55173025ab",
        "name": "Setswana",
        "local": 0,
        "lastupdate": 1707196143,
        "translated": 4
    },
    "scn": {
        "lang": "scn",
        "md5": "286fd343668126d534bd3ac63d3191e5",
        "name": "Sicilianu",
        "local": 0,
        "lastupdate": 1707196143,
        "translated": 39
    },
    "szl": {
        "lang": "szl",
        "md5": "d3e442ad4930b32bcb58d8a68655d04a",
        "name": "Ślōnski",
        "local": 476,
        "lastupdate": 1707196143,
        "translated": 2277
    },
    "sd_ap": {
        "lang": "sd_ap",
        "md5": "6a58cade7a58dfb974dd09441873c346",
        "name": "سنڌي",
        "local": 0,
        "lastupdate": 1707196143,
        "translated": 4
    },
    "si": {
        "lang": "si",
        "md5": "fe8757cb14c61ca917f130490ab3f2d4",
        "name": "සිංහල",
        "local": 0,
        "lastupdate": 1707196143,
        "translated": 1044
    },
    "sk": {
        "lang": "sk",
        "md5": "7c92abdf80a36a767cdddad09dfef50f",
        "name": "Slovenčina",
        "local": 0,
        "lastupdate": 1707196143,
        "translated": 1849
    },
    "sl": {
        "lang": "sl",
        "md5": "9dcc0db6c828aa801c11461120e89d30",
        "name": "Slovenščina",
        "local": 501,
        "lastupdate": 1707196143,
        "translated": 2347
    },
    "so": {
        "lang": "so",
        "md5": "de7dfa759f62dfdc1fa848ba32ccb173",
        "name": "Soomaali",
        "local": 0,
        "lastupdate": 1707196143,
        "translated": 333
    },
    "sma": {
        "lang": "sma",
        "md5": "066f0583815333dc93687bd81f4cb949",
        "name": "Sørsamisk",
        "local": 0,
        "lastupdate": 1707196143,
        "translated": 4
    },
    "es_ar": {
        "lang": "es_ar",
        "md5": "2a62c9288b7988aaa1e7107a77a9593c",
        "name": "Español - Argentina",
        "local": 0,
        "lastupdate": 1707196143,
        "translated": 96
    },
    "es_co": {
        "lang": "es_co",
        "md5": "df5107bf496629232220cc6f55a0c210",
        "name": "Español - Colombia",
        "local": 0,
        "lastupdate": 1707196143,
        "translated": 47
    },
    "es_mx": {
        "lang": "es_mx",
        "md5": "0ba4cd321cd7ffd8fa4f8c18eac127e0",
        "name": "Español - México",
        "local": 749,
        "lastupdate": 1707196143,
        "translated": 2745
    },
    "es_mx_kids": {
        "lang": "es_mx_kids",
        "md5": "a994d002e02cbdf1811c122f3d1f1f29",
        "name": "Español - México para niños",
        "local": 0,
        "lastupdate": 1707196143,
        "translated": 18
    },
    "es": {
        "lang": "es",
        "md5": "03e8b20e6e054c39337e4f76369045f8",
        "name": "Español - Internacional",
        "local": 748,
        "lastupdate": 1707196143,
        "translated": 2664
    },
    "es_ve": {
        "lang": "es_ve",
        "md5": "ad5ed0ad6fca668d67957cadf2db5ed5",
        "name": "Español - Venezuela",
        "local": 0,
        "lastupdate": 1707196143,
        "translated": 21
    },
    "es_wp": {
        "lang": "es_wp",
        "md5": "48cffbd3a6af81aa620696979814bfe5",
        "name": "Español para la Empresa",
        "local": 0,
        "lastupdate": 1707196143,
        "translated": 89
    },
    "sw": {
        "lang": "sw",
        "md5": "073eca007d1455d4710ed540d7521f4a",
        "name": "Kiswahili",
        "local": 0,
        "lastupdate": 1707196143,
        "translated": 175
    },
    "sv_fi": {
        "lang": "sv_fi",
        "md5": "169bbf48fed0e5588bde7cf94dea650e",
        "name": "Finlandssvenska",
        "local": 0,
        "lastupdate": 1707196143,
        "translated": 360
    },
    "sv": {
        "lang": "sv",
        "md5": "33ad2393b480d4f63c3cc75f08537c80",
        "name": "Svenska",
        "local": 607,
        "lastupdate": 1707196143,
        "translated": 2474
    },
    "sv_wp": {
        "lang": "sv_wp",
        "md5": "ce106b02ecfb829875348904dc7035f1",
        "name": "Svenska för Workplace",
        "local": 0,
        "lastupdate": 1707196143,
        "translated": 88
    },
    "tl": {
        "lang": "tl",
        "md5": "8d35732924be521b2e92dac89e2ec2a4",
        "name": "Tagalog",
        "local": 0,
        "lastupdate": 1707196143,
        "translated": 831
    },
    "tg": {
        "lang": "tg",
        "md5": "24c40ba6fe07aa28735b90f13c07f898",
        "name": "Тоҷикӣ",
        "local": 42,
        "lastupdate": 1707196143,
        "translated": 1261
    },
    "ta_lk": {
        "lang": "ta_lk",
        "md5": "07a6eba0f4e5ea38fbab91aa2de99cc5",
        "name": "தமிழ்",
        "local": 0,
        "lastupdate": 1707196143,
        "translated": 953
    },
    "ta": {
        "lang": "ta",
        "md5": "812d9fc1a0bdea1b60f1b67f1fe10c6c",
        "name": "Tamil",
        "local": 0,
        "lastupdate": 1707196143,
        "translated": 759
    },
    "tt": {
        "lang": "tt",
        "md5": "252bc1bd4d1e8c0afc06ef9d4f8d8c96",
        "name": "Татар",
        "local": 0,
        "lastupdate": 1707196143,
        "translated": 16
    },
    "te": {
        "lang": "te",
        "md5": "57277f3a5bdd3cec772122dc3c2d4c64",
        "name": "తెలుగు ",
        "local": 0,
        "lastupdate": 1707196143,
        "translated": 1112
    },
    "tet": {
        "lang": "tet",
        "md5": "536ea165f70a5bacef7db9bef23a3eea",
        "name": "Tetun Dili",
        "local": 0,
        "lastupdate": 1707196143,
        "translated": 3
    },
    "th": {
        "lang": "th",
        "md5": "b29d2857b834fa102a8d1b82fb542fb5",
        "name": "Thai",
        "local": 0,
        "lastupdate": 1707196143,
        "translated": 797
    },
    "xct": {
        "lang": "xct",
        "md5": "6fa9a30d9e0eed28aa8d27c3819ed3db",
        "name": "Tibetan",
        "local": 0,
        "lastupdate": 1707196143,
        "translated": 6
    },
    "ti": {
        "lang": "ti",
        "md5": "b459ef7b90eb6ab6b700a774b548563d",
        "name": "ትግርኛ",
        "local": 20,
        "lastupdate": 1707196143,
        "translated": 677
    },
    "tpi": {
        "lang": "tpi",
        "md5": "90badbe4a1f40685a2d0355f9303616b",
        "name": "Tok Pisin",
        "local": 0,
        "lastupdate": 1707196143,
        "translated": 177
    },
    "to": {
        "lang": "to",
        "md5": "f3de686d4cc9d366e189678b66a36725",
        "name": "Tongan",
        "local": 0,
        "lastupdate": 1707196143,
        "translated": 620
    },
    "tr": {
        "lang": "tr",
        "md5": "30498d7710ed5b40648a796abdc60508",
        "name": "Türkçe",
        "local": 748,
        "lastupdate": 1707196143,
        "translated": 2660
    },
    "tk": {
        "lang": "tk",
        "md5": "9af2470eeb00895ca87c73074c52c317",
        "name": "Turkmen",
        "local": 0,
        "lastupdate": 1707196144,
        "translated": 462
    },
    "uk": {
        "lang": "uk",
        "md5": "b2c8048993f61221d128d7377c0db6c0",
        "name": "Українська",
        "local": 603,
        "lastupdate": 1707196144,
        "translated": 2501
    },
    "hsb": {
        "lang": "hsb",
        "md5": "525a17148077f40770da858b9e0c90a2",
        "name": "Hornjoserbsce",
        "local": 341,
        "lastupdate": 1707196144,
        "translated": 1670
    },
    "ur": {
        "lang": "ur",
        "md5": "0805dc3ba67711fd629e3a31f8ed53bb",
        "name": "اردو",
        "local": 0,
        "lastupdate": 1707196144,
        "translated": 1747
    },
    "ug_lt": {
        "lang": "ug_lt",
        "md5": "77ce45617ba59a0961e9b339f23d1f11",
        "name": "Uyghur - latin",
        "local": 0,
        "lastupdate": 1707196144,
        "translated": 3
    },
    "ug_ug": {
        "lang": "ug_ug",
        "md5": "41375fcbf877a0a7d6d024ed607adb9f",
        "name": "ئۇيغۇرچە",
        "local": 1,
        "lastupdate": 1707196144,
        "translated": 213
    },
    "uz": {
        "lang": "uz",
        "md5": "18804eb2ffa462674be9d7d74bc4596f",
        "name": "O'zbekcha",
        "local": 468,
        "lastupdate": 1707196144,
        "translated": 1702
    },
    "ca_valencia_racv": {
        "lang": "ca_valencia_racv",
        "md5": "d9e8ff89042949c833afdcd912c031c1",
        "name": "Valencià_RACV",
        "local": 0,
        "lastupdate": 1707196144,
        "translated": 4
    },
    "vi": {
        "lang": "vi",
        "md5": "447bb278b81c64342a2868996c845f37",
        "name": "Vietnamese",
        "local": 433,
        "lastupdate": 1707196144,
        "translated": 1890
    },
    "cy": {
        "lang": "cy",
        "md5": "f17012eb8f3386b7c1c865463933e1f2",
        "name": "Cymraeg",
        "local": 0,
        "lastupdate": 1707196144,
        "translated": 1119
    },
    "wo": {
        "lang": "wo",
        "md5": "3d5844494370536b02cf6db206c2c55e",
        "name": "Wolof",
        "local": 0,
        "lastupdate": 1707196144,
        "translated": 61
    },
    "xh": {
        "lang": "xh",
        "md5": "1146b2175f08388bc4c748cdab4bb4f5",
        "name": "isiXhosa",
        "local": 0,
        "lastupdate": 1707196144,
        "translated": 3
    },
    "yo": {
        "lang": "yo",
        "md5": "bee71916ca11d79e4424d516d78182c3",
        "name": "Yorùbá",
        "local": 0,
        "lastupdate": 1707196144,
        "translated": 3
    },
    "zu": {
        "lang": "zu",
        "md5": "f6bb79cf1dbc54a6fa21213008a0ce63",
        "name": "isiZulu",
        "local": 0,
        "lastupdate": 1707196144,
        "translated": 510
    },
    "pt_br_kids": {
        "lang": "pt_br_kids",
        "md5": "7c9785567cca66f589bf9f19ff47fb71",
        "name": "Português Brasil para Crianças",
        "local": 0,
        "lastupdate": 1707196143,
        "translated": 70
    },
    "pt_br_uni": {
        "lang": "pt_br_uni",
        "md5": "1f2f7f67e6b14addb1b9b296afa53f96",
        "name": "Português Brasil para Universidades",
        "local": 32,
        "lastupdate": 1707196143,
        "translated": 109
    }
}
